raygun/__init__.py
raygun/fluorescentloader.py
raygun/loader.py
raygun/metrics.py
raygun/pll.py
raygun/train_utils.py
raygun/commands/__init__.py
raygun/commands/generate_samples.py
raygun/commands/train.py
raygun/model/__init__.py
raygun/model/esmdecoder.py
raygun/model/fluorescentmodel.py
raygun/model/model_utils.py
raygun/model/raygun.py
raygun/model/reduction.py
raygun/model/repitition.py
raygun-0.1.1.dist-info/LICENSE
raygun-0.1.1.dist-info/METADATA
raygun-0.1.1.dist-info/WHEEL
raygun-0.1.1.dist-info/entry_points.txt
raygun-0.1.1.dist-info/top_level.txt
raygun-0.1.1.dist-info/RECORD
