Metadata-Version: 2.1
Name: raygun
Version: 0.1.1
Summary: Protein Redesign using Raygun
Home-page: https://github.com/rohitsinghlab/raygun
Author: Kapil Devkota
Author-email: kapil.devkota@duke.edu
Classifier: Programming Language :: Python :: 3
Classifier: License :: OSI Approved :: MIT License
Classifier: Operating System :: OS Independent
Requires-Python: >=3.9
License-File: LICENSE
Requires-Dist: numpy
Requires-Dist: pandas
Requires-Dist: torch
Requires-Dist: fair-esm
Requires-Dist: tqdm
Requires-Dist: biopython
Requires-Dist: h5py
Requires-Dist: einops
Requires-Dist: pyyaml
